README.md
README.rst
setup.py
gidown/__init__.py
gidown/advanced.py
gidown/query.py
gidown/search.py
gidown.egg-info/PKG-INFO
gidown.egg-info/SOURCES.txt
gidown.egg-info/dependency_links.txt
gidown.egg-info/requires.txt
gidown.egg-info/top_level.txt
gidown.egg-info/zip-safe