Metadata-Version: 1.1
Name: gidown
Version: 0.1.0
Summary: Wrapper library for Google Image Search
Home-page: https://github.com/bonsaihr/gidown
Author: BonsAI d.o.o
Author-email: opensource@bonsai.hr
License: Apache 2.0
Keywords: google image search download wrapper
Platform: UNKNOWN
Classifier: Development Status :: 4 - Beta
Classifier: Topic :: Utilities
Classifier: License :: OSI Approved :: Apache Software License
